minknow/__init__.py
minknow/rpc/__init__.py
minknow/rpc/acquisition_pb2.py
minknow/rpc/acquisition_pb2_grpc.py
minknow/rpc/device_pb2.py
minknow/rpc/device_pb2_grpc.py
minknow/rpc/instance_pb2.py
minknow/rpc/instance_pb2_grpc.py
minknow/rpc/keystore_pb2.py
minknow/rpc/keystore_pb2_grpc.py
minknow/rpc/manager_pb2.py
minknow/rpc/manager_pb2_grpc.py
minknow/rpc/protocol_pb2.py
minknow/rpc/protocol_pb2_grpc.py
minknow/rpc/rpc_options_pb2.py
minknow/rpc/rpc_options_pb2_grpc.py
pyminknow/__init__.py
pyminknow/__main__.py
pyminknow/client.py
pyminknow/config.py
pyminknow/server.py
pyminknow/service/__init__.py
pyminknow/service/device.py
pyminknow/service/manager.py
pyminknow/service/protocol.py
pyminknow/tests/__init__.py
pyminknow/tests/test_device.py
pyminknow/tests/test_manager.py
pyminknow/tests/test_protocol.py
pyminknow/tests/client/__init__.py
pyminknow/tests/client/test_device.py
pyminknow/tests/client/test_manager.py
pyminknow-1.0.3.dist-info/LICENSE
pyminknow-1.0.3.dist-info/METADATA
pyminknow-1.0.3.dist-info/WHEEL
pyminknow-1.0.3.dist-info/top_level.txt
pyminknow-1.0.3.dist-info/RECORD
