Metadata-Version: 2.1
Name: pyminknow
Version: 1.0.3
Summary: This service mimics a Nanopore minKNOW gene sequencing device by using its gRPC interface.
Home-page: https://github.com/Joe-Heffer-Shef/pyminknow
Author: Joe Heffer
Author-email: j.heffer@sheffield.ac.uk
License: UNKNOWN
Platform: UNKNOWN
Classifier: Programming Language :: Python :: 3
Classifier: License :: OSI Approved :: MIT License
Classifier: Operating System :: OS Independent
Requires-Python: >=3.6
Requires-Dist: minknow-api (~=4.0)
